django_patango/__init__.py
django_patango/urls.py
django_patango/utils.py
django_patango/views.py
django_patango/static/django_patango/angular-app.js
django_patango/static/django_patango/angular-route.js
django_patango/static/django_patango/angular-sanitize.js
django_patango/static/django_patango/angular-translate.min.js
django_patango/static/django_patango/angular.js
django_patango/static/django_patango/bootstrap.min.js
django_patango/static/django_patango/jquery.min.js
django_patango/static/django_patango/lodash.js
django_patango/static/django_patango/select.js
django_patango/static/django_patango/templates.js
django_patango/static/django_patango/vendor.css
django_patango/static/django_patango/fonts/glyphicons-halflings-regular.eot
django_patango/static/django_patango/fonts/glyphicons-halflings-regular.svg
django_patango/static/django_patango/fonts/glyphicons-halflings-regular.ttf
django_patango/static/django_patango/fonts/glyphicons-halflings-regular.woff
django_patango/templates/django_patango/index.html
django_patango-0.2.0.dist-info/licenses/LICENSE
django_patango-0.2.0.dist-info/METADATA
django_patango-0.2.0.dist-info/WHEEL
django_patango-0.2.0.dist-info/top_level.txt
django_patango-0.2.0.dist-info/RECORD
