Metadata-Version: 2.4
Name: django-patango
Version: 0.2.0
Summary: A Django library with frontend integration
Author-email: Galech Mercado Alejandro <your@email.com>
License: MIT
Project-URL: Homepage, https://github.com/galech/patango
Project-URL: Bug Tracker, https://github.com/galech/patango/issues
Project-URL: Source Code, https://github.com/galech/patango
Requires-Python: >=3.8
License-File: LICENSE
Requires-Dist: django>=3.0
Requires-Dist: pandas
Dynamic: license-file
